open_notebook/__init__.py
open_notebook/__main__.py
open_notebook/_compat.py
open_notebook/_typing.py
open_notebook/_typing_compat.py
open_notebook/cli.py
open_notebook/config.py
open_notebook/handler.py
open_notebook/py.typed
open_notebook/utils.py
open_notebook-0.2.0.dist-info/METADATA
open_notebook-0.2.0.dist-info/WHEEL
open_notebook-0.2.0.dist-info/entry_points.txt
open_notebook-0.2.0.dist-info/licenses/LICENSE
open_notebook-0.2.0.dist-info/RECORD
