Metadata-Version: 2.4
Name: open-notebook
Version: 0.2.0
Summary: Command line program to open jupyter notebooks from single server
Project-URL: Documentation, https://pages.nist.gov/open-notebook/
Project-URL: Homepage, https://github.com/usnistgov/open-notebook
Author-email: "William P. Krekelberg" <wpk@nist.gov>
License: NIST-PD
License-File: LICENSE
Keywords: open-notebook
Classifier: Development Status :: 2 - Pre-Alpha
Classifier: Intended Audience :: Science/Research
Classifier: License :: Public Domain
Classifier: Operating System :: OS Independent
Classifier: Programming Language :: Python
Classifier: Programming Language :: Python :: 3 :: Only
Classifier: Programming Language :: Python :: 3.8
Classifier: Programming Language :: Python :: 3.9
Classifier: Programming Language :: Python :: 3.10
Classifier: Programming Language :: Python :: 3.11
Classifier: Programming Language :: Python :: 3.12
Classifier: Programming Language :: Python :: 3.13
Classifier: Topic :: Scientific/Engineering
Requires-Python: <3.14,>=3.8
Requires-Dist: tomli; python_version < '3.11'
Requires-Dist: typing-extensions; python_version < '3.11'
